pright/__init__.py
pright/app.py
pright-0.0.1.dist-info/METADATA
pright-0.0.1.dist-info/WHEEL
pright-0.0.1.dist-info/top_level.txt
pright-0.0.1.dist-info/RECORD
